pika_mq_consumer/__init__.py
pika_mq_consumer/consumer.py
pika_mq_consumer/exceptions.py
pika_mq_consumer/http_client.py
pika_mq_consumer/uploader.py
pika_mq_consumer-1.2.0.dist-info/METADATA
pika_mq_consumer-1.2.0.dist-info/WHEEL
pika_mq_consumer-1.2.0.dist-info/top_level.txt
pika_mq_consumer-1.2.0.dist-info/RECORD
