Metadata-Version: 2.4
Name: pika-mq-consumer
Version: 1.2.0
Summary: 简化的RabbitMQ消费者包装器，提供类似npm包的简洁API
Author-email: pika-mq-consumer <iyahe29@gmail.com>
Maintainer-email: pika-mq-consumer <iyahe29@gmail.com>
License: MIT
Project-URL: Homepage, https://github.com/yourusername/pika-mq-consumer
Project-URL: Documentation, https://pika-mq-consumer.readthedocs.io/
Project-URL: Repository, https://github.com/yourusername/pika-mq-consumer.git
Project-URL: Bug Tracker, https://github.com/yourusername/pika-mq-consumer/issues
Project-URL: Changelog, https://github.com/yourusername/pika-mq-consumer/blob/main/CHANGELOG.md
Keywords: rabbitmq,pika,mq,message-queue,consumer,amqp
Classifier: Development Status :: 5 - Production/Stable
Classifier: Intended Audience :: Developers
Classifier: Topic :: Software Development :: Libraries :: Python Modules
Classifier: Topic :: System :: Networking
Classifier: Topic :: Internet
Classifier: Programming Language :: Python :: 3
Classifier: Programming Language :: Python :: 3.7
Classifier: Programming Language :: Python :: 3.8
Classifier: Programming Language :: Python :: 3.9
Classifier: Programming Language :: Python :: 3.10
Classifier: Programming Language :: Python :: 3.11
Classifier: Programming Language :: Python :: 3.12
Classifier: Operating System :: OS Independent
Requires-Python: >=3.7
Requires-Dist: pika>=1.3.0
Requires-Dist: requests>=2.25.0
Provides-Extra: dev
Requires-Dist: pytest>=6.0; extra == "dev"
Requires-Dist: pytest-cov>=2.0; extra == "dev"
Requires-Dist: black>=21.0; extra == "dev"
Requires-Dist: flake8>=3.8; extra == "dev"
Requires-Dist: mypy>=0.900; extra == "dev"
Provides-Extra: docs
Requires-Dist: sphinx>=4.0; extra == "docs"
Requires-Dist: sphinx-rtd-theme>=1.0; extra == "docs"
